LICENSE.txt
MANIFEST.in
README.rst
requirements.txt
setup.py
riker/__init__.py
riker/api.py
riker/boto_helpers.py
riker/config.py
riker/git_helpers.py
riker/main.py
riker/retry.py
riker/utils.py
riker/version.py
riker.egg-info/PKG-INFO
riker.egg-info/SOURCES.txt
riker.egg-info/dependency_links.txt
riker.egg-info/entry_points.txt
riker.egg-info/requires.txt
riker.egg-info/top_level.txt